AddSub/carryGen.v
// This module generates the carries of 4 bit binary additions simultaneously

module carryGen(input [3:0]G,P, input Cin, output wire [3:0]C, output wire Cout);

//Cx means the carry required to generate Sx(x bit of Sum)
assign C[0] = Cin;
assign C[1] = G[0] | (Cin  & P[0]);
assign C[2] = G[1] | G[0]&P[1] | Cin &P[0]&P[1];
assign C[3] = G[2] | G[1]&P[2] | G[0]&P[1]&P[2] | Cin&P[0]&P[1]&P[2];
assign Cout = G[3] | G[2]&P[3] | G[1]&P[2]&P[3] | G[0]&P[1]&P[2]&P[3] | Cin&P[0]&P[1]&P[2]&P[3];

endmodule

AddSub/fourBitAdder.v
//This module describes the 4 bit adder carry look ahead adder

module fourBitAdder(input [3:0]A,B, input Cin, output [3:0]S, output Cout,CinMSB);
wire [3:0] G,P,C;

carryGen carryGen(.G(G), .P(P), .Cin(Cin), .C(C), .Cout(Cout));

assign G[3:0]=A[3:0] & B[3:0];
assign P[3:0]=A[3:0] ^ B[3:0];

assign S[3:0]=P[3:0] ^ C[3:0];

//Exposing the Carry into MSB for access in the Adder Subtractor module
//This is necessary to identify Overflow in Signed arithmetic
assign CinMSB = C[3];

endmodule

AddSub/tb4bitAdder.v
module tb4bitAdder();

reg [3:0] A, B;
reg Cin;
wire [3:0] S;
wire Cout;

fourBitAdder uut(.A(A), .B(B), .Cin(Cin), .S(S), .Cout(Cout));

initial begin
    $dumpfile("adder_var_dump.vcd");
    $dumpvars(0,tb4bitAdder);
end

initial begin
    A=4'd0; B=4'd0; Cin=0;  #10;
    A=4'd0; B=4'd1; Cin=1;  #10;
    A=4'd0; B=4'd2; Cin=0;  #10;
    A=4'd2; B=4'd4; Cin=1;  #10;
    A=4'd3; B=4'd6; Cin=0;  #10;
    A=4'd4; B=4'd7; Cin=1;  #10;
    A=4'd9; B=4'd6; Cin=0;  #10;
    A=4'd15;B=4'd15;Cin=0;  #10;
    A=4'd15;B=4'd15;Cin=1;  #10;

    $finish;
end
endmodule

AddSub/adder_var_dump.vcd
$date
	Wed Apr  2 17:41:35 2025
$end
$version
	Icarus Verilog
$end
$timescale
	1s
$end
$scope module tb4bitAdder $end
$var wire 4 ! S [3:0] $end
$var wire 1 " Cout $end
$var reg 4 # A [3:0] $end
$var reg 4 $ B [3:0] $end
$var reg 1 % Cin $end
$scope module uut $end
$var wire 4 & A [3:0] $end
$var wire 4 ' B [3:0] $end
$var wire 1 % Cin $end
$var wire 4 ( G [3:0] $end
$var wire 4 ) P [3:0] $end
$var wire 4 * S [3:0] $end
$var wire 1 " Cout $end
$var wire 1 + CinMSB $end
$var wire 4 , C [3:0] $end
$scope module carryGen $end
$var wire 1 % Cin $end
$var wire 1 " Cout $end
$var wire 4 - G [3:0] $end
$var wire 4 . P [3:0] $end
$var wire 4 / C [3:0] $end
$upscope $end
$upscope $end
$upscope $end
$enddefinitions $end
$comment Show the parameter values. $end
$dumpall
$end
#0
$dumpvars
b0 /
b0 .
b0 -
b0 ,
0+
b0 *
b0 )
b0 (
b0 '
b0 &
0%
b0 $
b0 #
0"
b0 !
$end
#10
b10 !
b10 *
b11 ,
b11 /
b1 )
b1 .
1%
b1 $
b1 '
#20
b10 !
b10 *
b0 ,
b0 /
b10 )
b10 .
0%
b10 $
b10 '
#30
b111 !
b111 *
b1 ,
b1 /
b110 )
b110 .
1%
b100 $
b100 '
b10 #
b10 &
#40
1+
b1001 !
b1001 *
b1100 ,
b1100 /
b10 (
b10 -
b101 )
b101 .
0%
b110 $
b110 '
b11 #
b11 &
#50
b1100 !
b1100 *
b1111 ,
b1111 /
b100 (
b100 -
b11 )
b11 .
1%
b111 $
b111 '
b100 #
b100 &
#60
0+
b1111 !
b1111 *
b0 ,
b0 /
b0 (
b0 -
b1111 )
b1111 .
0%
b110 $
b110 '
b1001 #
b1001 &
#70
1+
1"
b1110 ,
b1110 /
b1110 !
b1110 *
b1111 (
b1111 -
b0 )
b0 .
b1111 $
b1111 '
b1111 #
b1111 &
#80
b1111 !
b1111 *
b1111 ,
b1111 /
1%
