logicUnit/logic_unit.v
module logic_unit(input [31:0]A, B, input [1:0]sel, output [31:0]R);

wire [31:0] andout;
wire [31:0] orout;
wire [31:0] xorout;
wire [31:0] zero;

assign andout = A & B;
assign orout  = A | B;
assign xorout = A ^ B;
assign zero   = 32'd0;

//For 00->AND, 01->OR, 10->XOR
mux4to1 mux(.P(andout), .Q(orout), .R(xorout), .S(zero), .sel(sel), .y(R));

endmodule



// 4:1 32 bit multiplexer
module mux4to1(input[1:0] sel, input [31:0]P,Q,R,S, output reg [31:0]y);
always @(*)begin
    case(sel)
        2'b00 : y = P;
        2'b01 : y = Q;
        2'b10 : y = R;
        2'b11 : y = S;
    endcase
end
endmodule

logicUnit/tb_logic_unit.v
module tb_logic_unit();

reg [31:0]A,B; 
reg [1:0] sel;

wire [31:0] f;

logic_unit uut(.A(A), .B(B), .sel(sel), .R(f));

initial begin
    $dumpfile("var_dump.vcd");
    $dumpvars(0, tb_logic_unit);
end

initial begin
    A = 32'hFFFFFFFF; B = 32'hFFFFFFFF;
    sel = 2'b00;
    #10;
    sel = 2'b01;
    #10;
    sel = 2'b10;


    #10;
    A = 32'hFFFFFAB; B = 32'hABCFFFAB;
    sel = 2'b00;
    #10;
    sel = 2'b01;
    #10;
    sel = 2'b10;

    #10;
    A = 32'hF3FFFAB; B = 32'hA5CFFFAB;
    sel = 2'b00;
    #10;
    sel = 2'b01;
    #10;
    sel = 2'b10;
    #10;

    $finish;
end
endmodule

logicUnit/var_dump.vcd
$date
	Sat May 10 10:54:26 2025
$end
$version
	Icarus Verilog
$end
$timescale
	1s
$end
$scope module tb_logic_unit $end
$var wire 32 ! f [31:0] $end
$var reg 32 " A [31:0] $end
$var reg 32 # B [31:0] $end
$var reg 2 $ sel [1:0] $end
$scope module uut $end
$var wire 32 % A [31:0] $end
$var wire 32 & B [31:0] $end
$var wire 32 ' andout [31:0] $end
$var wire 32 ( orout [31:0] $end
$var wire 2 ) sel [1:0] $end
$var wire 32 * xorout [31:0] $end
$var wire 32 + zero [31:0] $end
$var wire 32 , R [31:0] $end
$scope module mux $end
$var wire 32 - P [31:0] $end
$var wire 32 . Q [31:0] $end
$var wire 32 / R [31:0] $end
$var wire 32 0 S [31:0] $end
$var wire 2 1 sel [1:0] $end
$var reg 32 2 y [31:0] $end
$upscope $end
$upscope $end
$upscope $end
$enddefinitions $end
$comment Show the parameter values. $end
$dumpall
$end
#0
$dumpvars
b11111111111111111111111111111111 2
b0 1
b0 0
b0 /
b11111111111111111111111111111111 .
b11111111111111111111111111111111 -
b11111111111111111111111111111111 ,
b0 +
b0 *
b0 )
b11111111111111111111111111111111 (
b11111111111111111111111111111111 '
b11111111111111111111111111111111 &
b11111111111111111111111111111111 %
b0 $
b11111111111111111111111111111111 #
b11111111111111111111111111111111 "
b11111111111111111111111111111111 !
$end
#10
b1 $
b1 )
b1 1
#20
b0 !
b0 ,
b0 2
b10 $
b10 )
b10 1
#30
b1011110011111111111110101011 !
b1011110011111111111110101011 ,
b1011110011111111111110101011 2
b1011110011111111111110101011 '
b1011110011111111111110101011 -
b10101111111111111111111110101011 (
b10101111111111111111111110101011 .
b10100100001100000000000000000000 *
b10100100001100000000000000000000 /
b0 $
b0 )
b0 1
b10101011110011111111111110101011 #
b10101011110011111111111110101011 &
b1111111111111111111110101011 "
b1111111111111111111110101011 %
#40
b10101111111111111111111110101011 !
b10101111111111111111111110101011 ,
b10101111111111111111111110101011 2
b1 $
b1 )
b1 1
#50
b10100100001100000000000000000000 !
b10100100001100000000000000000000 ,
b10100100001100000000000000000000 2
b10 $
b10 )
b10 1
#60
b101000011111111111110101011 !
b101000011111111111110101011 ,
b101000011111111111110101011 2
b101000011111111111110101011 '
b101000011111111111110101011 -
b10101010111100000000000000000000 *
b10101010111100000000000000000000 /
b0 $
b0 )
b0 1
b10100101110011111111111110101011 #
b10100101110011111111111110101011 &
b1111001111111111111110101011 "
b1111001111111111111110101011 %
#70
b10101111111111111111111110101011 !
b10101111111111111111111110101011 ,
b10101111111111111111111110101011 2
b1 $
b1 )
b1 1
#80
b10101010111100000000000000000000 !
b10101010111100000000000000000000 ,
b10101010111100000000000000000000 2
b10 $
b10 )
b10 1
